{
  "family": "bg",
  "level": "BG3",
  "comment": "3 switches, 8:1 contrast; 4 regimes; static BG models severely mis-locate events",
  "horizon": 50.0,
  "n_sequences": 60,
  "split": {
    "train": {
      "n": 40,
      "seeds": [
        0,
        39
      ]
    },
    "val": {
      "n": 10,
      "seeds": [
        40,
        49
      ]
    },
    "test": {
      "n": 10,
      "seeds": [
        50,
        59
      ]
    }
  },
  "dgp": {
    "domain": {
      "type": "rectangle",
      "x_min": 0.0,
      "x_max": 1.0,
      "y_min": 0.0,
      "y_max": 1.0
    },
    "kernel": {
      "type": "separable",
      "temporal_decay": 0.3,
      "spatial_sigma": 0.08
    },
    "background": {
      "type": "regime_switching",
      "lambda0": 1.5,
      "regimes": [
        {
          "t_start": 0.0,
          "t_end": 12.5,
          "components": [
            {
              "cx": 0.2,
              "cy": 0.2,
              "sigma": 0.12,
              "amplitude": 10.5
            }
          ]
        },
        {
          "t_start": 12.5,
          "t_end": 25.0,
          "components": [
            {
              "cx": 0.8,
              "cy": 0.2,
              "sigma": 0.12,
              "amplitude": 10.5
            }
          ]
        },
        {
          "t_start": 25.0,
          "t_end": 37.5,
          "components": [
            {
              "cx": 0.5,
              "cy": 0.8,
              "sigma": 0.12,
              "amplitude": 10.5
            }
          ]
        },
        {
          "t_start": 37.5,
          "t_end": 50.0,
          "components": [
            {
              "cx": 0.2,
              "cy": 0.7,
              "sigma": 0.12,
              "amplitude": 10.5
            }
          ]
        }
      ]
    },
    "adjacency": [
      [
        33.15727981081154
      ]
    ],
    "lambda_max_used": 277.2582384864923
  },
  "stats_all": {
    "n_sequences": 60,
    "mean": 187.78333333333333,
    "std": 22.02732520202023,
    "min": 150,
    "p25": 170.0,
    "p50": 184.0,
    "p75": 205.0,
    "p95": 226.0,
    "max": 236
  },
  "stats_train": {
    "n_sequences": 40,
    "mean": 184.05,
    "std": 19.865736835063533,
    "min": 151,
    "p25": 170.0,
    "p50": 182.0,
    "p75": 198.25,
    "p95": 217.45,
    "max": 226
  }
}