{
  "family": "bg",
  "level": "BG5",
  "comment": "hardest: 4 regimes, 8:1 contrast + two-scale echo (rho=30); all assumptions broken",
  "horizon": 50.0,
  "n_sequences": 60,
  "split": {
    "train": {
      "n": 40,
      "seeds": [
        0,
        39
      ]
    },
    "val": {
      "n": 10,
      "seeds": [
        40,
        49
      ]
    },
    "test": {
      "n": 10,
      "seeds": [
        50,
        59
      ]
    }
  },
  "dgp": {
    "domain": {
      "type": "rectangle",
      "x_min": 0.0,
      "x_max": 1.0,
      "y_min": 0.0,
      "y_max": 1.0
    },
    "kernel": {
      "type": "two_scale",
      "alpha_fast": 0.65,
      "beta_fast": 0.3,
      "beta_slow": 9.0,
      "sigma": 0.08
    },
    "background": {
      "type": "regime_switching",
      "lambda0": 1.5,
      "regimes": [
        {
          "t_start": 0.0,
          "t_end": 12.5,
          "components": [
            {
              "cx": 0.2,
              "cy": 0.2,
              "sigma": 0.12,
              "amplitude": 10.5
            }
          ]
        },
        {
          "t_start": 12.5,
          "t_end": 25.0,
          "components": [
            {
              "cx": 0.8,
              "cy": 0.2,
              "sigma": 0.12,
              "amplitude": 10.5
            }
          ]
        },
        {
          "t_start": 25.0,
          "t_end": 37.5,
          "components": [
            {
              "cx": 0.5,
              "cy": 0.8,
              "sigma": 0.12,
              "amplitude": 10.5
            }
          ]
        },
        {
          "t_start": 37.5,
          "t_end": 50.0,
          "components": [
            {
              "cx": 0.2,
              "cy": 0.7,
              "sigma": 0.12,
              "amplitude": 10.5
            }
          ]
        }
      ]
    },
    "adjacency": [
      [
        2.9927364354616546
      ]
    ],
    "lambda_max_used": 35.94189148369324
  },
  "stats_all": {
    "n_sequences": 60,
    "mean": 169.1,
    "std": 18.28177598958409,
    "min": 116,
    "p25": 156.0,
    "p50": 168.0,
    "p75": 180.0,
    "p95": 199.29999999999998,
    "max": 210
  },
  "stats_train": {
    "n_sequences": 40,
    "mean": 166.625,
    "std": 18.11171927233856,
    "min": 116,
    "p25": 156.0,
    "p50": 165.5,
    "p75": 178.0,
    "p95": 199.29999999999998,
    "max": 210
  }
}